{
  "num_rows": 10,
  "num_cols": 10,
  "comments": [
    "Word usage summary by score:",
    "Score 10: 6/69 words used (15.00% of puzzle, 8.70% of score group)",
    "Score 9: 1/28 words used (2.50% of puzzle, 3.57% of score group)",
    "Score 8: 2/14 words used (5.00% of puzzle, 14.29% of score group)",
    "Score 7: 1/6 words used (2.50% of puzzle, 16.67% of score group)",
    "Score 6: 0/3 words used (0.00% of puzzle, 0.00% of score group)",
    "Score 5: 0/3 words used (0.00% of puzzle, 0.00% of score group)",
    "Score 1: 20/3263 words used (50.00% of puzzle, 0.61% of score group)",
    "Score 0: 10/7929 words used (25.00% of puzzle, 0.13% of score group)",
    "Total: 40/11315 words used"
  ],
  "clues": [
    {
      "direction": "down-right",
      "clue_row": 0,
      "clue_col": 0,
      "solution": "חוסרצניעות",
      "definition": "indecency",
      "lengths": [
        4,
        6
      ]
    },
    {
      "direction": "down",
      "clue_row": 0,
      "clue_col": 0,
      "solution": "חד",
      "definition": "astute",
      "lengths": [
        2
      ]
    },
    {
      "direction": "left-down",
      "clue_row": 0,
      "clue_col": 9,
      "solution": "עוני",
      "definition": "poverty",
      "lengths": [
        4
      ]
    },
    {
      "direction": "down",
      "clue_row": 0,
      "clue_col": 9,
      "solution": "תופ",
      "definition": "tambourine",
      "lengths": [
        3
      ]
    },
    {
      "direction": "up-right",
      "clue_row": 9,
      "clue_col": 0,
      "solution": "צלול",
      "definition": "lucid",
      "lengths": [
        4
      ]
    },
    {
      "direction": "right-down",
      "clue_row": 0,
      "clue_col": 3,
      "solution": "חצ",
      "definition": "dart",
      "lengths": [
        2
      ]
    },
    {
      "direction": "right",
      "clue_row": 2,
      "clue_col": 4,
      "solution": "רצונו",
      "definition": "his will",
      "lengths": [
        5
      ]
    },
    {
      "direction": "down",
      "clue_row": 2,
      "clue_col": 4,
      "solution": "גס",
      "definition": "gross",
      "lengths": [
        2
      ]
    },
    {
      "direction": "down",
      "clue_row": 6,
      "clue_col": 6,
      "solution": "רב",
      "definition": "copious",
      "lengths": [
        2
      ]
    },
    {
      "direction": "right",
      "clue_row": 6,
      "clue_col": 6,
      "solution": "מות",
      "definition": "the death of",
      "lengths": [
        3
      ]
    },
    {
      "direction": "right",
      "clue_row": 3,
      "clue_col": 1,
      "solution": "לעג",
      "definition": "derision",
      "lengths": [
        3
      ]
    },
    {
      "direction": "down",
      "clue_row": 3,
      "clue_col": 1,
      "solution": "שפנסלע",
      "definition": "hyrax",
      "lengths": [
        3,
        3
      ]
    },
    {
      "direction": "right",
      "clue_row": 9,
      "clue_col": 2,
      "solution": "בוצ",
      "definition": "mire",
      "lengths": [
        3
      ]
    },
    {
      "direction": "down",
      "clue_row": 0,
      "clue_col": 2,
      "solution": "סמל",
      "definition": "emblem",
      "lengths": [
        3
      ]
    },
    {
      "direction": "left-down",
      "clue_row": 0,
      "clue_col": 2,
      "solution": "סוג",
      "definition": "species",
      "lengths": [
        3
      ]
    },
    {
      "direction": "down",
      "clue_row": 4,
      "clue_col": 8,
      "solution": "וו",
      "definition": "hook",
      "lengths": [
        2
      ]
    },
    {
      "direction": "down",
      "clue_row": 3,
      "clue_col": 5,
      "solution": "רק",
      "definition": "merely",
      "lengths": [
        2
      ]
    },
    {
      "direction": "right",
      "clue_row": 3,
      "clue_col": 5,
      "solution": "חריפ",
      "definition": "severe",
      "lengths": [
        4
      ]
    },
    {
      "direction": "down",
      "clue_row": 2,
      "clue_col": 3,
      "solution": "עמדה",
      "definition": "standpoint",
      "lengths": [
        4
      ]
    },
    {
      "direction": "right",
      "clue_row": 8,
      "clue_col": 4,
      "solution": "רבערכ",
      "definition": "invaluable",
      "lengths": [
        2,
        3
      ]
    },
    {
      "direction": "left-down",
      "clue_row": 8,
      "clue_col": 4,
      "solution": "לב",
      "definition": "heart",
      "lengths": [
        2
      ]
    },
    {
      "direction": "down",
      "clue_row": 4,
      "clue_col": 7,
      "solution": "אמצעי",
      "definition": "measure",
      "lengths": [
        5
      ]
    },
    {
      "direction": "down",
      "clue_row": 4,
      "clue_col": 2,
      "solution": "חלפו",
      "definition": "passed",
      "lengths": [
        4
      ]
    },
    {
      "direction": "right",
      "clue_row": 4,
      "clue_col": 2,
      "solution": "מסרו",
      "definition": "gave",
      "lengths": [
        4
      ]
    },
    {
      "direction": "right",
      "clue_row": 9,
      "clue_col": 6,
      "solution": "יעל",
      "definition": "ibex",
      "lengths": [
        3
      ]
    },
    {
      "direction": "down",
      "clue_row": 7,
      "clue_col": 9,
      "solution": "כל",
      "definition": "all",
      "lengths": [
        2
      ]
    },
    {
      "direction": "down-right",
      "clue_row": 3,
      "clue_col": 0,
      "solution": "דש",
      "definition": "lapel",
      "lengths": [
        2
      ]
    },
    {
      "direction": "up-right",
      "clue_row": 3,
      "clue_col": 0,
      "solution": "דגמ",
      "definition": "sampler",
      "lengths": [
        3
      ]
    },
    {
      "direction": "down",
      "clue_row": 7,
      "clue_col": 8,
      "solution": "רע",
      "definition": "wicked",
      "lengths": [
        2
      ]
    },
    {
      "direction": "right",
      "clue_row": 6,
      "clue_col": 0,
      "solution": "נלהב",
      "definition": "ardent",
      "lengths": [
        4
      ]
    },
    {
      "direction": "right",
      "clue_row": 5,
      "clue_col": 0,
      "solution": "פחד",
      "definition": "consternation",
      "lengths": [
        3
      ]
    },
    {
      "direction": "right",
      "clue_row": 7,
      "clue_col": 3,
      "solution": "נמרצ",
      "definition": "emphatic",
      "lengths": [
        4
      ]
    },
    {
      "direction": "left-down",
      "clue_row": 0,
      "clue_col": 7,
      "solution": "ניצחונ",
      "definition": "conquest",
      "lengths": [
        6
      ]
    },
    {
      "direction": "down",
      "clue_row": 0,
      "clue_col": 7,
      "solution": "עור",
      "definition": "skin",
      "lengths": [
        3
      ]
    },
    {
      "direction": "right",
      "clue_row": 7,
      "clue_col": 0,
      "solution": "ספ",
      "definition": "verge",
      "lengths": [
        2
      ]
    },
    {
      "direction": "down",
      "clue_row": 6,
      "clue_col": 5,
      "solution": "מרצ",
      "definition": "zeal",
      "lengths": [
        3
      ]
    },
    {
      "direction": "left-down",
      "clue_row": 6,
      "clue_col": 5,
      "solution": "בנ",
      "definition": "son",
      "lengths": [
        2
      ]
    },
    {
      "direction": "down",
      "clue_row": 4,
      "clue_col": 9,
      "solution": "תת",
      "definition": "hypo-",
      "lengths": [
        2
      ]
    },
    {
      "direction": "right",
      "clue_row": 5,
      "clue_col": 4,
      "solution": "קנאות",
      "definition": "bigotry",
      "lengths": [
        5
      ]
    },
    {
      "direction": "down",
      "clue_row": 0,
      "clue_col": 5,
      "solution": "נר",
      "definition": "candle",
      "lengths": [
        2
      ]
    }
  ],
  "mask_id": "mask_3",
  "score_distribution": {
    "1": 20,
    "9": 1,
    "10": 6,
    "8": 2,
    "7": 1,
    "0": 10
  }
}